llm_accounting/__init__.py
llm_accounting/audit_log.py
llm_accounting/db_migrations.py
llm_accounting/version_cache.py
llm_accounting/backends/__init__.py
llm_accounting/backends/base.py
llm_accounting/backends/mock_backend.py
llm_accounting/backends/postgresql.py
llm_accounting/backends/sqlite.py
llm_accounting/backends/sqlite_queries.py
llm_accounting/backends/sqlite_utils.py
llm_accounting/backends/mock_backend_parts/connection_manager.py
llm_accounting/backends/mock_backend_parts/limit_manager.py
llm_accounting/backends/mock_backend_parts/query_executor.py
llm_accounting/backends/mock_backend_parts/stats_manager.py
llm_accounting/backends/mock_backend_parts/usage_manager.py
llm_accounting/backends/postgresql_backend_parts/connection_manager.py
llm_accounting/backends/postgresql_backend_parts/data_deleter.py
llm_accounting/backends/postgresql_backend_parts/data_inserter.py
llm_accounting/backends/postgresql_backend_parts/limit_manager.py
llm_accounting/backends/postgresql_backend_parts/project_manager.py
llm_accounting/backends/postgresql_backend_parts/query_executor.py
llm_accounting/backends/postgresql_backend_parts/query_reader.py
llm_accounting/backends/postgresql_backend_parts/quota_reader.py
llm_accounting/backends/postgresql_backend_parts/schema_manager.py
llm_accounting/backends/postgresql_backend_parts/user_manager.py
llm_accounting/backends/sqlite_backend_parts/audit_log_manager.py
llm_accounting/backends/sqlite_backend_parts/connection_manager.py
llm_accounting/backends/sqlite_backend_parts/limit_manager.py
llm_accounting/backends/sqlite_backend_parts/project_manager.py
llm_accounting/backends/sqlite_backend_parts/query_executor.py
llm_accounting/backends/sqlite_backend_parts/quota_rejection_manager.py
llm_accounting/backends/sqlite_backend_parts/usage_manager.py
llm_accounting/backends/sqlite_backend_parts/user_manager.py
llm_accounting/cli/main.py
llm_accounting/cli/parsers.py
llm_accounting/cli/utils.py
llm_accounting/cli/commands/limits.py
llm_accounting-0.1.34.dist-info/METADATA
llm_accounting-0.1.34.dist-info/WHEEL
llm_accounting-0.1.34.dist-info/entry_points.txt
llm_accounting-0.1.34.dist-info/licenses/LICENSE
llm_accounting-0.1.34.dist-info/RECORD
