Metadata-Version: 2.4
Name: llm-accounting
Version: 0.1.34
Summary: A package for tracking LLM usage and costs
Author-email: Mateusz <matdev83@github.com>
License-File: LICENSE
Requires-Python: >=3.8
Requires-Dist: alembic>=1.7.0
Requires-Dist: cachetools==5.3.3
Requires-Dist: click==8.1.7
Requires-Dist: colorama==0.4.6
Requires-Dist: packaging>=24.1
Requires-Dist: psycopg2-binary<3.0,>=2.9
Requires-Dist: python-dotenv==1.0.1
Requires-Dist: pytz==2024.1
Requires-Dist: rich>=10.0.0
Requires-Dist: sqlalchemy>=2.0.0
Requires-Dist: typer==0.12.3
Provides-Extra: dev
Requires-Dist: build; extra == 'dev'
Requires-Dist: coverage==7.5.4; extra == 'dev'
Requires-Dist: faker==25.0.0; extra == 'dev'
Requires-Dist: freezegun==1.5.1; extra == 'dev'
Requires-Dist: pytest-asyncio==0.23.7; extra == 'dev'
Requires-Dist: pytest-cov==5.0.0; extra == 'dev'
Requires-Dist: pytest-mock==3.14.0; extra == 'dev'
Requires-Dist: pytest==8.3.5; extra == 'dev'
Requires-Dist: toml>=0.10.2; extra == 'dev'
Requires-Dist: twine; extra == 'dev'
Requires-Dist: virtualenv; extra == 'dev'
Provides-Extra: mysql
Requires-Dist: aiomysql>=0.1.1; extra == 'mysql'
Provides-Extra: neon
Provides-Extra: postgresql
Requires-Dist: asyncpg>=0.25.0; extra == 'postgresql'
Provides-Extra: sqlite
Requires-Dist: aiosqlite>=0.17.0; extra == 'sqlite'
